
[
   {
     "id": "cold-apetizer-1",
     "категорія": "Холодні Закуски: ",
     "назва": "М'ясне асорті",
     "інгредієнти": "Балик, с/к, н/к",
     "вага": "150гр",
     "ціна": "130-00"
     
   },
   {
     "id": "cold-apetizer-2",
     "категорія": "Холодні Закуски: ",
     "назва": "Овочеве асорті",
     "інгредієнти": [],
     "вага": "300гр",
     "ціна": "130-00"
   },
   {
     "id": "cold-apetizer-3",
     "категорія": "Холодні Закуски: ",
     "назва": "Сирне асорті",
     "інгредієнти": [],
     "вага": "150гр",
     "ціна": "120-00"
   },
   {
     "id": "cold-apetizer-4",
     "категорія": "Холодні Закуски: ",
     "назва": "Бринза з кінзою",
     "інгредієнти": [],
     "вага": "110гр",
     "ціна": "100-00"
   },
   {
     "id": "cold-apetizer-5",
     "категорія": "Холодні Закуски: ",
     "назва": "Зелень",
     "інгредієнти": [],
     "вага": "50гр",
     "ціна": "80-00"
   },
   {
     "id": "cold-apetizer-6",
     "категорія": "Холодні Закуски: ",
     "назва": "Сьомга слабосолена",
     "інгредієнти": [],
     "вага": "60/10гр",
     "ціна": "150-00"
   },
   {
     "id": "cold-apetizer-7",
     "категорія": "Холодні Закуски: ",
     "назва": "Оселедець з цибулею",
     "інгредієнти": [],
     "вага": "110гр",
     "ціна": "100-00"
   },
   {
     "id": "cold-apetizer-8",
     "категорія": "Холодні Закуски: ",
     "назва": "Закуска Царська",
     "інгредієнти": [],
     "вага": "210гр",
     "ціна": "115-00"
   },
   {
     "id": "cold-apetizer-9",
     "категорія": "Холодні Закуски: ",
     "назва": "Ікра по царськи",
     "інгредієнти": [],
     "вага": "50/100/50гр",
     "ціна": "220-00"
   },
   {
     "id": "cold-apetizer-10",
     "категорія": "Холодні Закуски: ",
     "назва": "Млинці з ікрою",
     "інгредієнти": [],
     "вага": "100/30гр",
     "ціна": "105-00"
   },
   {
     "id": "cold-apetizer-11",
     "категорія": "Холодні Закуски: ",
     "назва": "Канапки з ікрою",
     "інгредієнти": [],
     "вага": "60гр",
     "ціна": "100-00"
   },
   {
     "id": "cold-apetizer-12",
     "категорія": "Холодні Закуски: ",
     "назва": "Канапки з сьомгою",
     "інгредієнти": [],
     "вага": "90гр",
     "ціна": "120-00"
   },
   {
     "id": "cold-apetizer-13",
     "категорія": "Холодні Закуски: ",
     "назва": "Яйця фаршировані печінкою тріски",
     "інгредієнти": [],
     "вага": "180гр",
     "ціна": "90-00"
   },
   {
     "id": "cold-apetizer-14",
     "категорія": "Холодні Закуски: ",
     "назва": "Помідори фаршировані печінкою тріски",
     "інгредієнти": [],
     "вага": "250гр",
     "ціна": "90-00"
   },
   {
     "id": "cold-apetizer-15",
     "категорія": "Холодні Закуски: ",
     "назва": "Помідори фаршировані грибами",
     "інгредієнти": [],
     "вага": "250гр",
     "ціна": "85-00"
   },
   {
     "id": "cold-apetizer-16",
     "категорія": "Холодні Закуски: ",
     "назва": "Гриби мариновані",
     "інгредієнти": [],
     "вага": "100гр",
     "ціна": "65-00"
     
   },
   {
     "id": "cold-apetizer-17",
     "категорія": "Холодні Закуски: ",
     "назва": "Соління",
     "інгредієнти": [],
     "вага": "300гр",
     "ціна": "100-00"
     
   },
   {
     "id": "cold-apetizer-18",
     "категорія": "Холодні Закуски: ",
     "назва": "Маслини, оливки",
     "інгредієнти": [],
     "вага": "50гр",
     "ціна": "60-00"
     
   },
   {
     "id": "cold-apetizer-19",
     "категорія": "Холодні Закуски: ",
     "назва": "Язик під майонезом",
     "інгредієнти": [],
     "вага": "70/50гр",
     "ціна": "130-00"
     
   },
   {
     "id": "cold-apetizer-20",
     "категорія": "Холодні Закуски: ",
     "назва": "Шпиг",
     "інгредієнти": "Перекручене сало з грінками",
     "вага": "100гр",
     "ціна": "80-00"
     
   },
   {
     "id": "cold-apetizer-21",
     "категорія": "Холодні Закуски: ",
     "назва": "Сало з хріном",
     "інгредієнти": [],
     "вага": "100гр",
     "ціна": "80-00"
     
   },
   {
     "id": "cold-apetizer-22",
     "категорія": "Холодні Закуски: ",
     "назва": "Хліб",
     "інгредієнти": [],
     "вага": "4 шт",
     "ціна": "10-00"
     
   }
 ]
 