[
   {
     "id": "ukrainian-wine-1",
     "категорія": "Вино: ",
     "назва": "Інкерман",

     "вага50": "50мл",
    "ціна50": "15-00",

    "вага100": "100мл",
    "ціна100": "30-00",

     "тип": "",
     "вага": "0.7л",
     "ціна": "225-00"
   },
   {
     "id": "ukrainian-wine-2",
     "категорія": "Вино: ",
     "назва": "Шабо",
     "інгредієнти": "біле",

     "вага50": "50мл",
    "ціна50": "15-00",

    "вага100": "100мл",
    "ціна100": "30-00",
    
     "вага": "0.7л",
     "ціна": "225-00"
     
   }, 
   {
    "id": "ukrainian-wine-3",
    "категорія": "Вино: ",
    "назва": "Шабо",
    "інгредієнти": "червоне сухе",

    "вага50": "50мл",
    "ціна50": "15-00",

    "вага100": "100мл",
    "ціна100": "30-00",

    "вага": "0.7л",
    "ціна": "225-00"
    
  }, {
    "id": "ukrainian-wine-4",
    "категорія": "Вино: ",
    "назва": "Шабо",
    "інгредієнти": "напівсолодке",

    "вага50": "50мл",
    "ціна50": "15-00",

    "вага100": "100мл",
    "ціна100": "30-00",

    "вага": "0.7л",
    "ціна": "225-00"
    
  }, {
    "id": "ukrainian-wine-5",
    "категорія": "Вино: ",
    "назва": "Шабо",
    "інгредієнти": "напівсухе",

    "вага50": "50мл",
    "ціна50": "15-00",

    "вага100": "100мл",
    "ціна100": "30-00",


    "вага": "0.7л",
    "ціна": "225-00"
    
  }
 ]

 