[
   {
     "id": "salad-1",
     "назва": "Салат айсберг з телячим язиком",
     "обєм": "250гр",
     "ціна": "120-00",
     "інгредієнти": ["айсберг", "тел.язик", "помідор", "пармезан", "медово-соєвий соус"]
   },
   {
     "id": "salad-2",
     "назва": "Салат з беконом і сиром",
     "обєм": "270гр",
     "ціна": "120-00",
     "інгредієнти": ["айсберг", "оливки", "бекон", "перець", "пармезан", "оливкова олія"]
   },
   {
     "id": "salad-3",
     "назва": "Фантазія",
     "обєм": "200гр",
     "ціна": "110-00",
     "інгредієнти": ["телячий язик", "огірки", "перець", "помідор", "майонез"]
   },
   {
     "id": "salad-4",
     "назва": "Салат айсберг з телятиною",
     "обєм": "200гр",
     "ціна": "130-00",
     "інгредієнти": ["айсберг", "телятина", "перець", "помідор", "пармезан", "соус"]
   },
   {
     "id": "salad-5",
     "назва": "Легкий",
     "обєм": "340гр",
     "ціна": "150-00",
     "інгредієнти": ["руколла", "апельсин", "курка", "морква", "яблуко", "соус"]
   },
   {
     "id": "salad-6",
     "назва": "Ніжність",
     "обєм": "250гр",
     "ціна": "130-00",
     "інгредієнти": ["руколла", "помідор", "сухарики", "кунжут", "пармезан", "соус"]
   },
   {
     "id": "salad-7",
     "назва": "Тбілісі",
     "обєм": "200гр",
     "ціна": "110-00",
     "інгредієнти": ["курка", "ананас", "сир", "гриби", "майонез"]
   },
   {
     "id": "salad-8",
     "назва": "Монако",
     "обєм": "200гр",
     "ціна": "110-00",
     "інгредієнти": ["перець", "гриби", "курка", "маслини", "майонез"]
   },
   {
     "id": "salad-9",
     "назва": "Каспій",
     "обєм": "200гр",
     "ціна": "130-00",
     "інгредієнти": ["руколла", "курка", "помідор", "кунжут"]
   },
   {
     "id": "salad-10",
     "назва": "Медея",
     "обєм": "200гр",
     "ціна": "120-00",
     "інгредієнти": ["шпинат", "курка", "фета", "перець", "помідор", "оливкова олія"]
   },
   {
     "id": "salad-11",
     "назва": "Від повара",
     "обєм": "200гр",
     "ціна": "110-00",
     "інгредієнти": ["вітчина", "сир", "ананас", "яйця", "майонез"]
   },
   {
     "id": "salad-12",
     "назва": "Гарячий салат",
     "обєм": "220гр",
     "ціна": "120-00",
     "інгредієнти": ["баклажани", "перець", "цибуля", "огірки", "курка", "кунжут"]
   },
   {
     "id": "salad-13",
     "назва": "Цезарь з куркою",
     "обєм": "200гр",
     "ціна": "130-00",
     "інгредієнти": ["айсберг", "курка", "пармезан", "сухарі", "соус", "помідор"]
   },
   {
     "id": "salad-14",
     "назва": "Бакінські зорі",
     "обєм": "230гр",
     "ціна": "130-00",
     "інгредієнти": ["язик", "сир", "авокадо", "огірки", "апельсин", "соус"]
   },
   {
     "id": "salad-15",
     "назва": "Чобан по-кавказьки",
     "обєм": "200гр",
     "ціна": "95-00",
     "інгредієнти": ["помідор", "огірок", "цибуля", "зелень", "лимонний сік"]
   },
   {
     "id": "salad-16",
     "назва": "Весна",
     "обєм": "200гр",
     "ціна": "90-00",
     "інгредієнти": ["капуста", "огірок", "зелень", "олія"]
   },
   {
     "id": "salad-17",
     "назва": "Салат зі свіжих овочів",
     "обєм": "200гр",
     "ціна": "90-00",
     "інгредієнти": ["помідор", "огірок", "перець", "олія"]
   },
   {
     "id": "salad-18",
     "назва": "Грецький",
     "обєм": "200гр",
     "ціна": "110-00",
     "інгредієнти": ["помідори", "огірки", "перець", "фета", "маслини", "оливкова олія"]
   },
   {
     "id": "salad-19",
     "назва": "Фатіма",
     "обєм": "200гр",
     "ціна": "110-00",
     "інгредієнти": ["айсберг", "гриби", "маслини", "огірки", "помідори", "кунжут", "оливкова олія"]
   },
   {
     "id": "salad-20",
     "назва": "Шопський",
     "обєм": "200гр",
     "ціна": "110-00",
     "інгредієнти": ["помідори", "перець", "бринза", "маслини", "оливкова олія"]
   },
   {
     "id": "salad-21",
     "назва": "Азарі",
     "обєм": "230гр",
     "ціна": "130-00",
     "інгредієнти": ["спаржа", "тунець", "каперси", "помідори", "оливкова олія"]
   },
   {
     "id": "salad-22",
     "назва": "Салат з тунцем,спаржою і фетою",
     "обєм": "320гр",
     "ціна": "135-00",
     "інгредієнти": ["айсберг", "помідори", "спаржа", "тунець", "фета", "соєвий соус", "оливкова олія"]
   },
   {
     "id": "salad-23",
     "назва": "Салат норвежський з сьомгою",
     "обєм": "350гр",
     "ціна": "160-00",
     "інгредієнти": ["айсберг", "спаржа", "сьомга с/с", "помідори", "пармезан", "оливкова олія"]
   },
   {
     "id": "salad-24",
     "назва": "Цезарь з сьомгою",
     "обєм": "250гр",
     "ціна": "150-00",
     "інгредієнти": ["айсберг", "сьомга", "пармезан", "сухарі", "оливкова олія"]
   },
   {
     "id": "salad-25",
     "назва": "Теплий з сьомгою",
     "обєм": "350гр",
     "ціна": "160-00",
     "інгредієнти": ["айсберг", "вершковий соус", "сьомга", "помідор", "гриби"]
   }
 ]
 